flexhash-1.0.0.dist-info/WHEEL
flexhash-1.0.0.dist-info/top_level.txt
flexhash-1.0.0.dist-info/METADATA
flexhash-1.0.0.dist-info/RECORD
flexhash-1.0.0.dist-info/licenses/LICENSE
flexhash/flex.h
flexhash/flex.c
flexhash/__init__.py
flexhash/_flexmodule.c
flexhash/_flexhash.cpython-312-x86_64-linux-musl.so
flexhash/crypto/skein_port.h
flexhash/crypto/c_skein.h
flexhash/crypto/hash.h
flexhash/crypto/c_blake256.c
flexhash/crypto/oaes_config.h
flexhash/crypto/c_blake256.h
flexhash/crypto/int-util.h
flexhash/crypto/hash-ops.h
flexhash/crypto/c_jh.c
flexhash/crypto/oaes_lib.c
flexhash/crypto/c_groestl.h
flexhash/crypto/blake.c
flexhash/crypto/oaes_lib.h
flexhash/crypto/blake.h
flexhash/crypto/aesb.c
flexhash/crypto/c_jh.h
flexhash/crypto/hash.c
flexhash/crypto/c_groestl.c
flexhash/crypto/groestl_tables.h
flexhash/crypto/sponge.c
flexhash/crypto/sponge.h
flexhash/crypto/c_skein.c
flexhash/crypto/variant2_int_sqrt.h
flexhash/crypto/c_keccak.h
flexhash/crypto/sysendian.h
flexhash/crypto/c_keccak.c
flexhash/crypto/cryptonote/cryptonight_soft_shell.c
flexhash/crypto/cryptonote/cryptonight_fast.c
flexhash/crypto/cryptonote/cryptonight_turtle_lite.h
flexhash/crypto/cryptonote/cryptonight.h
flexhash/crypto/cryptonote/cryptonight_lite.h
flexhash/crypto/cryptonote/cryptonight_turtle.c
flexhash/crypto/cryptonote/cryptonight_dark.c
flexhash/crypto/cryptonote/cryptonight_turtle_lite.c
flexhash/crypto/cryptonote/cryptonight_turtle.h
flexhash/crypto/cryptonote/cryptonight_dark.h
flexhash/crypto/cryptonote/cryptonight_dark_lite.h
flexhash/crypto/cryptonote/cryptonight_soft_shell.h
flexhash/crypto/cryptonote/cryptonight_fast.h
flexhash/crypto/cryptonote/cryptonight.c
flexhash/crypto/cryptonote/cryptonight_lite.c
flexhash/crypto/cryptonote/cryptonight_dark_lite.c
flexhash/crypto/sha3/sph_shavite.c
flexhash/crypto/sha3/sph_hamsi.c
flexhash/crypto/sha3/sph_types.h
flexhash/crypto/sha3/sph_bmw.c
flexhash/crypto/sha3/sph_gost.c
flexhash/crypto/sha3/sph_sha2.h
flexhash/crypto/sha3/haval_helper.c
flexhash/crypto/sha3/sph_sha2big.c
flexhash/crypto/sha3/sph_luffa.h
flexhash/crypto/sha3/sph_keccak.h
