Metadata-Version: 2.4
Name: flexhash
Version: 1.0.0
Summary: Kylacoin Flex hashing (C extension)
Home-page: https://github.com/cdonnachie/flexhash
Author: cdonnachie
Author-email: craig.donnachie@gmail.com
License: MIT
Keywords: hashing,cryptography,kylacoin,lyncoin,flex
Classifier: Development Status :: 4 - Beta
Classifier: Intended Audience :: Developers
Classifier: License :: OSI Approved :: MIT License
Classifier: Operating System :: POSIX :: Linux
Classifier: Operating System :: Microsoft :: Windows
Classifier: Programming Language :: Python :: 3
Classifier: Topic :: Security :: Cryptography
Classifier: Topic :: Software Development :: Libraries :: Python Modules
Requires-Python: >=3.8
License-File: LICENSE
Dynamic: author
Dynamic: author-email
Dynamic: classifier
Dynamic: description
Dynamic: description-content-type
Dynamic: home-page
Dynamic: keywords
Dynamic: license
Dynamic: license-file
Dynamic: requires-python
Dynamic: summary
